jupyterlab_infinstor/__init__.py
jupyterlab_infinstor/auth_helpers.py
jupyterlab_infinstor/cognito_utils.py
jupyterlab_infinstor/proxy.py
jupyterlab_infinstor/servicedefs.py
jupyterlab_infinstor/websocket.py
jupyterlab_infinstor/tests/__init__.py
jupyterlab_infinstor/tests/test_auth.py
jupyterlab_infinstor/tests/test_get_s3.py
jupyterlab_infinstor-2.0.21.data/data/etc/jupyter/jupyter_notebook_config.d/jupyterlab_infinstor.json
jupyterlab_infinstor-2.0.21.dist-info/METADATA
jupyterlab_infinstor-2.0.21.dist-info/WHEEL
jupyterlab_infinstor-2.0.21.dist-info/top_level.txt
jupyterlab_infinstor-2.0.21.dist-info/RECORD
