Metadata-Version: 2.1
Name: jupyterlab-infinstor
Version: 2.0.21
Summary: InfinStor Jupyter Server extension
Author: InfinStor, Inc.
Author-email: support@infinstor.com
License: AGPL-3.0
Keywords: Jupyter,JupyterLab,InfinStor,InfinSnap,InfinSlice
Platform: Linux
Platform: Mac OS X
Platform: Windows
Classifier: Intended Audience :: Developers
Classifier: Intended Audience :: Education
Classifier: Intended Audience :: Science/Research
Classifier: License :: OSI Approved :: GNU Affero General Public License v3 or later (AGPLv3+)
Classifier: Programming Language :: Python
Classifier: Programming Language :: Python :: 3
Requires-Python: >=3.5
Requires-Dist: notebook
Requires-Dist: boto3
Requires-Dist: jupyterlab (>=2)
Requires-Dist: aiohttp
Requires-Dist: jsons
